pydpack/__init__.py
pydpack/__main__.py
pydpack-0.0.2.dist-info/licenses/LICENSE
pydpack-0.0.2.dist-info/METADATA
pydpack-0.0.2.dist-info/WHEEL
pydpack-0.0.2.dist-info/entry_points.txt
pydpack-0.0.2.dist-info/top_level.txt
pydpack-0.0.2.dist-info/RECORD
