Metadata-Version: 2.4
Name: pydpack
Version: 0.0.2
Summary: This is a pydpack.
Author-email: axiner <atpuxiner@163.com>
Project-URL: Homepage, https://github.com/atpuxiner/pydpack
Classifier: Programming Language :: Python :: 3.11
Classifier: Operating System :: OS Independent
Requires-Python: >=3.11
License-File: LICENSE
Requires-Dist: toollib>=1.8.7
Requires-Dist: Cython>=3.1.6
Dynamic: license-file
